deface/__init__.py
deface/__main__.py
deface/cli.py
deface/error.py
deface/ingest.py
deface/logger.py
deface/model.py
deface/serde.py
deface/validator.py
deface_social-0.8.0.dist-info/entry_points.txt
deface_social-0.8.0.dist-info/LICENSE
deface_social-0.8.0.dist-info/WHEEL
deface_social-0.8.0.dist-info/METADATA
deface_social-0.8.0.dist-info/RECORD
