Metadata-Version: 2.1
Name: deface-social
Version: 0.8.0
Summary: Liberate your posts from Facebook
Author-email: Robert Grimm <apparebit@gmail.com>
Requires-Python: >=3.9
Classifier: Environment :: Console
Classifier: License :: OSI Approved :: Apache Software License
Classifier: Operating System :: OS Independent
Classifier: Programming Language :: Python :: 3.9
Classifier: Topic :: Text Processing
Classifier: Topic :: Utilities
Requires-Dist: flit ; extra == "dev"
Requires-Dist: furo ; extra == "doc"
Requires-Dist: sphinx ; extra == "doc"
Requires-Dist: sphinx-argparse-cli ; extra == "doc"
Requires-Dist: sphinxext-opengraph ; extra == "doc"
Requires-Dist: mypy ; extra == "test"
Requires-Dist: pytest ; extra == "test"
Requires-Dist: pytest-cov ; extra == "test"
Project-URL: Changelog, https://apparebit.github.io/deface/changelog.html
Project-URL: Documentation, https://apparebit.github.io/deface/
Project-URL: Source, https://github.com/apparebit/deface
Provides-Extra: dev
Provides-Extra: doc
Provides-Extra: test
